runtime_typing/__init__.py
runtime_typing/typed.py
runtime_typing/typed_function.py
runtime_typing/utils.py
runtime_typing/violations.py
runtime_typing-1.0.0.dist-info/LICENSE.txt
runtime_typing-1.0.0.dist-info/METADATA
runtime_typing-1.0.0.dist-info/WHEEL
runtime_typing-1.0.0.dist-info/top_level.txt
runtime_typing-1.0.0.dist-info/RECORD
